{"nodes": ["h1", "h2", "h3", "h4", "h5", "h6", "s1"], "links": [{"src": "h1", "dst": "s1", "bw": 55, "delay": "17ms"}, {"src": "h2", "dst": "s1", "bw": 58, "delay": "20ms"}, {"src": "h3", "dst": "s1", "bw": 14, "delay": "13ms"}, {"src": "h4", "dst": "s1", "bw": 53, "delay": "1ms"}, {"src": "h5", "dst": "s1", "bw": 74, "delay": "1ms"}, {"src": "h6", "dst": "s1", "bw": 44, "delay": "1ms"}], "flows": [{"src": "h6", "dst": "h3", "rate": 14}, {"src": "h4", "dst": "h1", "rate": 15}, {"src": "h5", "dst": "h3", "rate": 9}, {"src": "h3", "dst": "h1", "rate": 8}]}